odoo/addons/website_form_metadata/README.rst
odoo/addons/website_form_metadata/__init__.py
odoo/addons/website_form_metadata/__manifest__.py
odoo/addons/website_form_metadata/i18n/website_form_metadata.pot
odoo/addons/website_form_metadata/models/__init__.py
odoo/addons/website_form_metadata/models/res_config_settings.py
odoo/addons/website_form_metadata/readme/CONFIGURE.rst
odoo/addons/website_form_metadata/readme/CONTRIBUTORS.rst
odoo/addons/website_form_metadata/readme/DESCRIPTION.rst
odoo/addons/website_form_metadata/readme/USAGE.rst
odoo/addons/website_form_metadata/static/description/icon.png
odoo/addons/website_form_metadata/static/description/index.html
odoo/addons/website_form_metadata/views/res_config_view.xml
odoo11_addon_website_form_metadata-11.0.1.0.0.99.dev13.dist-info/METADATA
odoo11_addon_website_form_metadata-11.0.1.0.0.99.dev13.dist-info/WHEEL
odoo11_addon_website_form_metadata-11.0.1.0.0.99.dev13.dist-info/top_level.txt
odoo11_addon_website_form_metadata-11.0.1.0.0.99.dev13.dist-info/RECORD
